PyForgeAPI/__init__.py
PyForgeAPI/classes/__init__.py
PyForgeAPI/classes/body.py
PyForgeAPI/classes/cors.py
PyForgeAPI/classes/database.py
PyForgeAPI/classes/file.py
PyForgeAPI/classes/form.py
PyForgeAPI/classes/handler.py
PyForgeAPI/classes/handler_exception.py
PyForgeAPI/classes/request.py
PyForgeAPI/classes/response.py
PyForgeAPI/classes/server.py
PyForgeAPI/classes/timer.py
PyForgeAPI/constants/__init__.py
PyForgeAPI/constants/content_type.py
PyForgeAPI/decorators/__init__.py
PyForgeAPI/decorators/module.py
PyForgeAPI/decorators/routes.py
PyForgeAPI/exceptions/__init__.py
PyForgeAPI/exceptions/duplicate_route.py
PyForgeAPI/exceptions/file.py
PyForgeAPI/exceptions/invalid_path.py
PyForgeAPI/exceptions/response.py
PyForgeAPI/functions/__init__.py
PyForgeAPI/functions/build_route_path.py
PyForgeAPI/functions/ready.py
PyForgeAPI-1.4.0.dist-info/LICENSE
PyForgeAPI-1.4.0.dist-info/METADATA
PyForgeAPI-1.4.0.dist-info/WHEEL
PyForgeAPI-1.4.0.dist-info/top_level.txt
PyForgeAPI-1.4.0.dist-info/RECORD
