Metadata-Version: 2.1
Name: PyForgeAPI
Version: 1.4.0
Summary: PyForgeAPI is a fast and easy-to-use open source python library for developing RESTful APIs. It provides a clear and concise syntax for handling routes, requests, and responses, making the development of APIs faster and more efficient. With support for form parameters, body and route parameters, it is useful for handling different types of requests. Whether you are a beginner or an experienced developer, PyForgeAPI is a simple and powerful choice for creating robust and scalable APIs.
Home-page: https://github.com/luisviniciuslv/PyForgeAPI
Author: Viinilv
Author-email: luisvpersy@gmail.com
Project-URL: Bug Tracker, https://github.com/luisviniciuslv/PyForgeAPI/issues
Classifier: Programming Language :: Python :: 3
Classifier: License :: OSI Approved :: GNU Affero General Public License v3
Classifier: Operating System :: OS Independent
Requires-Python: >=3.6
License-File: LICENSE
